{
    "bookSourceGroup": "🎨漫画,self",
    "bookSourceName": "包子漫画",
    "bookSourceType": 2,
    "bookSourceUrl": "https://www.baozimh.com/",
    "customOrder": 0,
    "enabled": true,
    "enabledCookieJar": true,
    "enabledExplore": true,
    "exploreUrl": "[\n    {\n        \"title\": \"区域\",\n        \"url\": \"\",\n        \"style\": {\n            \"layout_flexBasisPercent\": 1,\n            \"layout_flexGrow\": 1\n        }\n    },\n    {\n        \"title\": \"全部\",\n        \"url\": \"https://www.baozimh.com/api/bzmhq/amp_comic_list?type=all&region=all&state=all&filter=*&page={{page}}&limit=50&language=cn&__amp_source_origin=https%3A%2F%2Fwww.baozimh.com\"\n    },\n    {\n        \"title\": \"國漫\",\n        \"url\": \"https://www.baozimh.com/api/bzmhq/amp_comic_list?type=all&region=cn&state=all&filter=*&page={{page}}&limit=50&language=cn&__amp_source_origin=https%3A%2F%2Fwww.baozimh.com\"\n    },\n    {\n        \"title\": \"日本\",\n        \"url\": \"https://www.baozimh.com/api/bzmhq/amp_comic_list?type=all&region=jp&state=all&filter=*&page={{page}}&limit=50&language=cn&__amp_source_origin=https%3A%2F%2Fwww.baozimh.com\"\n    },\n    {\n        \"title\": \"韓國\",\n        \"url\": \"https://www.baozimh.com/api/bzmhq/amp_comic_list?type=all&region=kr&state=all&filter=*&page={{page}}&limit=50&language=cn&__amp_source_origin=https%3A%2F%2Fwww.baozimh.com\"\n    },\n    {\n        \"title\": \"歐美\",\n        \"url\": \"https://www.baozimh.com/api/bzmhq/amp_comic_list?type=all&region=en&state=all&filter=*&page={{page}}&limit=50&language=cn&__amp_source_origin=https%3A%2F%2Fwww.baozimh.com\"\n    },\n    {\n        \"title\": \"状态\",\n        \"url\": \"\",\n        \"style\": {\n            \"layout_flexBasisPercent\": 1,\n            \"layout_flexGrow\": 1\n        }\n    },\n    {\n        \"title\": \"全部\",\n        \"url\": \"https://www.baozimh.com/api/bzmhq/amp_comic_list?type=all&region=all&state=all&filter=*&page={{page}}&limit=50&language=cn&__amp_source_origin=https%3A%2F%2Fwww.baozimh.com\"\n    },\n    {\n        \"title\": \"連載中\",\n        \"url\": \"https://www.baozimh.com/api/bzmhq/amp_comic_list?type=all&region=all&state=serial&filter=*&page={{page}}&limit=50&language=cn&__amp_source_origin=https%3A%2F%2Fwww.baozimh.com\"\n    },\n    {\n        \"title\": \"已完結\",\n        \"url\": \"https://www.baozimh.com/api/bzmhq/amp_comic_list?type=all&region=all&state=pub&filter=*&page={{page}}&limit=50&language=cn&__amp_source_origin=https%3A%2F%2Fwww.baozimh.com\"\n    },\n    {\n        \"title\": \"分类\",\n        \"url\": \"\",\n        \"style\": {\n            \"layout_flexBasisPercent\": 1,\n            \"layout_flexGrow\": 1\n        }\n    },\n    {\n        \"title\": \"全部\",\n        \"url\": \"https://www.baozimh.com/api/bzmhq/amp_comic_list?type=all&region=all&state=all&filter=*&page={{page}}&limit=50&language=cn&__amp_source_origin=https%3A%2F%2Fwww.baozimh.com\"\n    },\n    {\n        \"title\": \"戀愛\",\n        \"url\": \"https://www.baozimh.com/api/bzmhq/amp_comic_list?type=lianai&region=all&state=all&filter=*&page={{page}}&limit=50&language=cn&__amp_source_origin=https%3A%2F%2Fwww.baozimh.com\"\n    },\n    {\n        \"title\": \"純愛\",\n        \"url\": \"https://www.baozimh.com/api/bzmhq/amp_comic_list?type=chunai&region=all&state=all&filter=*&page={{page}}&limit=50&language=cn&__amp_source_origin=https%3A%2F%2Fwww.baozimh.com\"\n    },\n    {\n        \"title\": \"古風\",\n        \"url\": \"https://www.baozimh.com/api/bzmhq/amp_comic_list?type=gufeng&region=all&state=all&filter=*&page={{page}}&limit=50&language=cn&__amp_source_origin=https%3A%2F%2Fwww.baozimh.com\"\n    },\n    {\n        \"title\": \"異能\",\n        \"url\": \"https://www.baozimh.com/api/bzmhq/amp_comic_list?type=yineng&region=all&state=all&filter=*&page={{page}}&limit=50&language=cn&__amp_source_origin=https%3A%2F%2Fwww.baozimh.com\"\n    },\n    {\n        \"title\": \"懸疑\",\n        \"url\": \"https://www.baozimh.com/api/bzmhq/amp_comic_list?type=xuanyi&region=all&state=all&filter=*&page={{page}}&limit=50&language=cn&__amp_source_origin=https%3A%2F%2Fwww.baozimh.com\"\n    },\n    {\n        \"title\": \"劇情\",\n        \"url\": \"https://www.baozimh.com/api/bzmhq/amp_comic_list?type=juqing&region=all&state=all&filter=*&page={{page}}&limit=50&language=cn&__amp_source_origin=https%3A%2F%2Fwww.baozimh.com\"\n    },\n    {\n        \"title\": \"科幻\",\n        \"url\": \"https://www.baozimh.com/api/bzmhq/amp_comic_list?type=kehuan&region=all&state=all&filter=*&page={{page}}&limit=50&language=cn&__amp_source_origin=https%3A%2F%2Fwww.baozimh.com\"\n    },\n    {\n        \"title\": \"奇幻\",\n        \"url\": \"https://www.baozimh.com/api/bzmhq/amp_comic_list?type=qihuan&region=all&state=all&filter=*&page={{page}}&limit=50&language=cn&__amp_source_origin=https%3A%2F%2Fwww.baozimh.com\"\n    },\n    {\n        \"title\": \"玄幻\",\n        \"url\": \"https://www.baozimh.com/api/bzmhq/amp_comic_list?type=xuanhuan&region=all&state=all&filter=*&page={{page}}&limit=50&language=cn&__amp_source_origin=https%3A%2F%2Fwww.baozimh.com\"\n    },\n    {\n        \"title\": \"穿越\",\n        \"url\": \"https://www.baozimh.com/api/bzmhq/amp_comic_list?type=chuanyue&region=all&state=all&filter=*&page={{page}}&limit=50&language=cn&__amp_source_origin=https%3A%2F%2Fwww.baozimh.com\"\n    },\n    {\n        \"title\": \"冒險\",\n        \"url\": \"https://www.baozimh.com/api/bzmhq/amp_comic_list?type=mouxian&region=all&state=all&filter=*&page={{page}}&limit=50&language=cn&__amp_source_origin=https%3A%2F%2Fwww.baozimh.com\"\n    },\n    {\n        \"title\": \"推理\",\n        \"url\": \"https://www.baozimh.com/api/bzmhq/amp_comic_list?type=tuili&region=all&state=all&filter=*&page={{page}}&limit=50&language=cn&__amp_source_origin=https%3A%2F%2Fwww.baozimh.com\"\n    },\n    {\n        \"title\": \"武俠\",\n        \"url\": \"https://www.baozimh.com/api/bzmhq/amp_comic_list?type=wuxia&region=all&state=all&filter=*&page={{page}}&limit=50&language=cn&__amp_source_origin=https%3A%2F%2Fwww.baozimh.com\"\n    },\n    {\n        \"title\": \"格鬥\",\n        \"url\": \"https://www.baozimh.com/api/bzmhq/amp_comic_list?type=gedou&region=all&state=all&filter=*&page={{page}}&limit=50&language=cn&__amp_source_origin=https%3A%2F%2Fwww.baozimh.com\"\n    },\n    {\n        \"title\": \"戰爭\",\n        \"url\": \"https://www.baozimh.com/api/bzmhq/amp_comic_list?type=zhanzheng&region=all&state=all&filter=*&page={{page}}&limit=50&language=cn&__amp_source_origin=https%3A%2F%2Fwww.baozimh.com\"\n    },\n    {\n        \"title\": \"熱血\",\n        \"url\": \"https://www.baozimh.com/api/bzmhq/amp_comic_list?type=rexie&region=all&state=all&filter=*&page={{page}}&limit=50&language=cn&__amp_source_origin=https%3A%2F%2Fwww.baozimh.com\"\n    },\n    {\n        \"title\": \"搞笑\",\n        \"url\": \"https://www.baozimh.com/api/bzmhq/amp_comic_list?type=gaoxiao&region=all&state=all&filter=*&page={{page}}&limit=50&language=cn&__amp_source_origin=https%3A%2F%2Fwww.baozimh.com\"\n    },\n    {\n        \"title\": \"大女主\",\n        \"url\": \"https://www.baozimh.com/api/bzmhq/amp_comic_list?type=danuzhu&region=all&state=all&filter=*&page={{page}}&limit=50&language=cn&__amp_source_origin=https%3A%2F%2Fwww.baozimh.com\"\n    },\n    {\n        \"title\": \"都市\",\n        \"url\": \"https://www.baozimh.com/api/bzmhq/amp_comic_list?type=dushi&region=all&state=all&filter=*&page={{page}}&limit=50&language=cn&__amp_source_origin=https%3A%2F%2Fwww.baozimh.com\"\n    },\n    {\n        \"title\": \"總裁\",\n        \"url\": \"https://www.baozimh.com/api/bzmhq/amp_comic_list?type=zongcai&region=all&state=all&filter=*&page={{page}}&limit=50&language=cn&__amp_source_origin=https%3A%2F%2Fwww.baozimh.com\"\n    },\n    {\n        \"title\": \"後宮\",\n        \"url\": \"https://www.baozimh.com/api/bzmhq/amp_comic_list?type=hougong&region=all&state=all&filter=*&page={{page}}&limit=50&language=cn&__amp_source_origin=https%3A%2F%2Fwww.baozimh.com\"\n    },\n    {\n        \"title\": \"日常\",\n        \"url\": \"https://www.baozimh.com/api/bzmhq/amp_comic_list?type=richang&region=all&state=all&filter=*&page={{page}}&limit=50&language=cn&__amp_source_origin=https%3A%2F%2Fwww.baozimh.com\"\n    },\n    {\n        \"title\": \"韓漫\",\n        \"url\": \"https://www.baozimh.com/api/bzmhq/amp_comic_list?type=hanman&region=all&state=all&filter=*&page={{page}}&limit=50&language=cn&__amp_source_origin=https%3A%2F%2Fwww.baozimh.com\"\n    },\n    {\n        \"title\": \"少年\",\n        \"url\": \"https://www.baozimh.com/api/bzmhq/amp_comic_list?type=shaonian&region=all&state=all&filter=*&page={{page}}&limit=50&language=cn&__amp_source_origin=https%3A%2F%2Fwww.baozimh.com\"\n    },\n    {\n        \"title\": \"其它\",\n        \"url\": \"https://www.baozimh.com/api/bzmhq/amp_comic_list?type=qita&region=all&state=all&filter=*&page={{page}}&limit=50&language=cn&__amp_source_origin=https%3A%2F%2Fwww.baozimh.com\"\n    },\n    {\n        \"title\": \"首字母\",\n        \"url\": \"\",\n        \"style\": {\n            \"layout_flexBasisPercent\": 1,\n            \"layout_flexGrow\": 1\n        }\n    },\n    {\n        \"title\": \"全部\",\n        \"url\": \"https://www.baozimh.com/api/bzmhq/amp_comic_list?type=all&region=all&state=all&filter=*&page={{page}}&limit=50&language=cn&__amp_source_origin=https%3A%2F%2Fwww.baozimh.com\"\n    },\n    {\n        \"title\": \"ABCD\",\n        \"url\": \"https://www.baozimh.com/api/bzmhq/amp_comic_list?type=all&region=all&state=all&filter=ABCD&page={{page}}&limit=50&language=cn&__amp_source_origin=https%3A%2F%2Fwww.baozimh.com\"\n    },\n    {\n        \"title\": \"EFGH\",\n        \"url\": \"https://www.baozimh.com/api/bzmhq/amp_comic_list?type=all&region=all&state=all&filter=EFGH&page={{page}}&limit=50&language=cn&__amp_source_origin=https%3A%2F%2Fwww.baozimh.com\"\n    },\n    {\n        \"title\": \"IJKL\",\n        \"url\": \"https://www.baozimh.com/api/bzmhq/amp_comic_list?type=all&region=all&state=all&filter=IJKL&page={{page}}&limit=50&language=cn&__amp_source_origin=https%3A%2F%2Fwww.baozimh.com\"\n    },\n    {\n        \"title\": \"MNOP\",\n        \"url\": \"https://www.baozimh.com/api/bzmhq/amp_comic_list?type=all&region=all&state=all&filter=MNOP&page={{page}}&limit=50&language=cn&__amp_source_origin=https%3A%2F%2Fwww.baozimh.com\"\n    },\n    {\n        \"title\": \"QRST\",\n        \"url\": \"https://www.baozimh.com/api/bzmhq/amp_comic_list?type=all&region=all&state=all&filter=QRST&page={{page}}&limit=50&language=cn&__amp_source_origin=https%3A%2F%2Fwww.baozimh.com\"\n    },\n    {\n        \"title\": \"UVW\",\n        \"url\": \"https://www.baozimh.com/api/bzmhq/amp_comic_list?type=all&region=all&state=all&filter=UVW&page={{page}}&limit=50&language=cn&__amp_source_origin=https%3A%2F%2Fwww.baozimh.com\"\n    },\n    {\n        \"title\": \"XYZ\",\n        \"url\": \"https://www.baozimh.com/api/bzmhq/amp_comic_list?type=all&region=all&state=all&filter=XYZ&page={{page}}&limit=50&language=cn&__amp_source_origin=https%3A%2F%2Fwww.baozimh.com\"\n    },\n    {\n        \"title\": \"0-9\",\n        \"url\": \"https://www.baozimh.com/api/bzmhq/amp_comic_list?type=all&region=all&state=all&filter=0-9&page={{page}}&limit=50&language=cn&__amp_source_origin=https%3A%2F%2Fwww.baozimh.com\"\n    }\n]",
    "lastUpdateTime": 1701762582358,
    "respondTime": 180000,
    "ruleBookInfo": {
        "author": ".comics-detail__author@text",
        "coverUrl": "tag.amp-img.0@src##\\?\\S*",
        "intro": ".comics-detail__desc@text",
        "kind": ".tag-list@class.tag@text",
        "lastChapter": ".comics-detail__info@a.0@text",
        "name": ".comics-detail__title@text",
        "wordCount": ""
    },
    "ruleContent": {
        "content": "class.comic-contain@tag.img@src<js>\nvar arr = result.split(\"\\n\")\narr.map(v => `<img src=\"${v}\" />`).join(\"\\n\")\n</js>",
        "nextContentUrl": "id.next-chapter@href<js>\nlet u = \"\";\nif (result[0]){\nlet re =  /\\/\\d+_\\d+_\\d+\\.html/;\nu = re.exec(result[0]) ? result[0] : \"\";\n}\nu\n</js>"
    },
    "ruleExplore": {
        "author": "author",
        "bookList": "items[*]",
        "bookUrl": "https://www.baozimh.com/comic/{{$.comic_id}}",
        "coverUrl": "https://static-tw.baozimh.com/cover/{{$.topic_img}}?w=285&h=375&q=100",
        "name": "name"
    },
    "ruleReview": {},
    "ruleSearch": {
        "author": ".tags@text",
        "bookList": ".comics-card",
        "bookUrl": "a.0@href",
        "coverUrl": "tag.amp-img.0@src",
        "kind": ".tab@text",
        "name": "h3@text"
    },
    "ruleToc": {
        "chapterList": ".comics-chapters a",
        "chapterName": "text",
        "chapterUrl": "href"
    },
    "searchUrl": "https://www.baozimh.com/search?q={{key}}",
    "weight": 0
}